{
    "request": {
        "type": "City",
        "query": "Chiang Mai, Thailand",
        "language": "en",
        "unit": "m"
    },
    "location": {
        "name": "Chiang Mai",
        "country": "Thailand",
        "region": "Chiang Mai",
        "lat": "18.790",
        "lon": "98.982",
        "timezone_id": "Asia/Bangkok",
        "localtime": "2024-09-01 11:38",
        "localtime_epoch": 1725190680,
        "utc_offset": "7.0"
    },
    "current": {
        "observation_time": "04:38 AM",
        "temperature": 27,
        "weather_code": 116,
        "weather_icons": [
            "https://cdn.worldweatheronline.com/images/wsymbols01_png_64/wsymbol_0002_sunny_intervals.png"
        ],
        "weather_descriptions": [
            "Partly cloudy"
        ],
        "wind_speed": 6,
        "wind_degree": 320,
        "wind_dir": "NW",
        "pressure": 1011,
        "precip": 0.1,
        "humidity": 79,
        "cloudcover": 75,
        "feelslike": 29,
        "uv_index": 7,
        "visibility": 10,
        "is_day": "yes"
    }
}